dorianUtils/Simulators.py
dorianUtils/__init__.py
dorianUtils/comUtils.py
dorianUtils/configFilesD.py
dorianUtils/dashTabsD.py
dorianUtils/dccExtendedD.py
dorianUtils/fitUtils.py
dorianUtils/mplExtended.py
dorianUtils/utilsD.py
dorianUtils/assets/styles.css
dorianUtils/conf/colormaps.pkl
dorianUtils/conf/logo_sylfen.png
dorianUtils/conf/palettes.pkl
dorianUtils/conf/units.csv
dorianUtils/sparkUtils/__init__.py
dorianUtils/sparkUtils/sparkDfUtils.py
dorianUtils/sparkUtils/sparkSqlDumpLoader.py
dorianUtilsModulaire-4.3.2.dist-info/METADATA
dorianUtilsModulaire-4.3.2.dist-info/WHEEL
dorianUtilsModulaire-4.3.2.dist-info/top_level.txt
dorianUtilsModulaire-4.3.2.dist-info/RECORD
