Metadata-Version: 2.1
Name: dorianUtilsModulaire
Version: 4.3.2
Summary: Utilities package
Home-page: UNKNOWN
Author: Dorian Drevon
Author-email: drevondorian@gmail.com
License: UNKNOWN
Platform: UNKNOWN
Classifier: Programming Language :: Python :: 3
Classifier: License :: OSI Approved :: MIT License
Classifier: Operating System :: OS Independent
Requires-Python: >=3.8
Requires-Dist: IPython (==7.20.0)
Requires-Dist: Pillow (==7.0.0)
Requires-Dist: cryptography (==2.8)
Requires-Dist: dash-auth (==1.4.1)
Requires-Dist: dash-daq (==0.5.0)
Requires-Dist: dash (==1.20.0)
Requires-Dist: dash-bootstrap-components (==0.13.0)
Requires-Dist: flask-caching
Requires-Dist: odfpy (==1.4.1)
Requires-Dist: opcua (==0.98.13)
Requires-Dist: pandas (==1.3.1)
Requires-Dist: psycopg2-binary
Requires-Dist: pymodbus (==2.5.3)
